[
   {
    "lagu": "https://d.top4top.io/m_2352gmwnh1.mp3",
    "judul": "Kaikai Kitan",
    "artis": "Eve"
   },
   {
    "lagu": "https://f.top4top.io/m_23528kjzx1.mp3",
    "judul": "EVERBLUE",
    "artis": "Omoinotake"
   },
   {
    "lagu": "https://f.top4top.io/m_2352e77qi1.mp3",
    "judul": "Bokura ga Orokadanante Dare ga Itta",
    "artis": "DIALOGUE+"
   },
   {
    "lagu": "https://e.top4top.io/m_23520dyfm1.mp3",
    "judul": "id:entity voices",
    "artis": "hololive indonesia"
   },
   {
    "lagu": "https://b.top4top.io/m_23527hmrg1.mp3",
    "judul": "kaika",
    "artis": "cadode"
   },
   {
    "lagu": "https://j.top4top.io/m_2352yo22g1.mp3",
    "judul": "Hoshi ga Oyogu",
    "artis": "Macaroni Enpitsu"
   },
   {
    "lagu": "https://d.top4top.io/m_2352zukpn1.mp3",
    "judul": "Comedy",
    "artis": "Gen Hosnino"
   },
   {
    "lagu": "https://d.top4top.io/m_2352dohgq1.mp3",
    "judul": "Mixed Nuts",
    "artis": "Official HIGE DANdsim"
   },
   {
    "lagu": "https://a.top4top.io/m_2352i3kmk1.mp3",
    "judul": "ALiCE&u",
    "artis": "Ayunda Risu"
   },
   {
    "lagu": "https://a.top4top.io/m_2352w2toa1.mp3",
    "judul": "High Tide",
    "artis": "Moona Hoshinova"
   },
   {
    "lagu": "https://l.top4top.io/m_2352a173m1.mp3",
    "judul": "FIRE BIRD",
    "artis": "Roselia"
   },
   {
    "lagu": "https://b.top4top.io/m_23524v60g1.mp3",
    "judul": "Hikare Inochi",
    "artis": "Kitri"
   },
   {
    "lagu": "https://i.top4top.io/m_2352tsbzl1.mp3",
    "judul": "Ao 100-iro",
    "artis": "Miku Itou"
   },
   {
    "lagu": "https://f.top4top.io/m_2352rpmnp1.mp3",
    "judul": "Sore Wo Ai To Yobudake",
    "artis": "Mafumafu"
   },
   {
    "lagu": "https://e.top4top.io/m_2352a23b71.mp3",
    "judul": "Freesia",
    "artis": "Uru"
   },
   {
    "lagu": "https://i.top4top.io/m_2352mo99a1.mp3",
    "judul": "HINOTORI",
    "artis": "Takanashi Kiara"
   },
   {
    "lagu": "https://i.top4top.io/m_2352l3vug1.mp3",
    "judul": "Bluerose",
    "artis": "Hoshimachi Suisei"
   },
   {
    "lagu": "https://c.top4top.io/m_2353b7s4r1.mp3",
    "judul": "SAKURA",
    "artis": "Ikimonogakari"
   },
   {
    "lagu": "https://c.top4top.io/m_23527l4rr1.mp3",
    "judul": "Orange",
    "artis": "7!!"
   },
   {
    "lagu": "https://a.top4top.io/m_2046fhj6y0.mp3",
    "judul": "Replica",
    "artis": "mol-74"
   },
   {
    "lagu": "https://d.top4top.io/m_23526z8xc1.mp3",
    "judul": "give it back",
    "artis": "Cö shu Nie"
   },
   {
    "lagu": "https://e.top4top.io/m_2352v0q361.mp3",
    "judul": "Vivid Vice",
    "artis": "Who-ya Extended"
   },
   {
    "lagu": "https://g.top4top.io/m_2352apvfz1.mp3",
    "judul": "Centimeter",
    "artis": "the peggies"
   },
   {
    "lagu": "https://i.top4top.io/m_2352ins521.mp3",
    "judul": "ninelie",
    "artis": "Aimer, Chelly"
   },
   {
    "lagu": "https://l.top4top.io/m_2352l3efq1.mp3",
    "judul": "DADDY ! DADDY ! DO !",
    "artis": "Masayuki Suzuki"
   },
   {
    "lagu": "https://a.top4top.io/m_2352i7t761.mp3",
    "judul": "GIRI GIRI",
    "artis": "Masayuki Suzuki"
   },
   {
    "lagu": "https://b.top4top.io/m_2352cwfbc1.mp3",
    "judul": "aLIEz",
    "artis": "SawanoHiroyuki[nZk]:mizuki"
   },
   {
    "lagu": "https://k.top4top.io/m_23527wt4o1.mp3",
    "judul": "Outsider",
    "artis": "Eve"
   },
   {
    "lagu": "https://i.top4top.io/m_23529pw2s1.mp3",
    "judul": "Sincerely",
    "artis": "TRUE"
   },
   {
    "lagu": "https://d.top4top.io/m_2352h3o0r1.mp3",
    "judul": "Kiminosei",
    "artis": "the peggies"
   },
   {
    "lagu": "https://a.top4top.io/m_2352abt7u1.mp3",
    "judul": "daydream cafe",
    "artis": "Petit Rabbit’s"
   },
   {
    "lagu": "https://j.top4top.io/m_2353ovuea1.mp3",
    "judul": "Chitty Chitty Bang Bang",
    "artis": "QUEENDOM"
   },
   {
    "lagu": "https://d.top4top.io/m_2353t3fep1.mp3",
    "judul": "Hatsukoi",
    "artis": "Nao Toyama"
   },
   {
    "lagu": "https://d.top4top.io/m_2353idv0k1.mp3",
    "judul": "Aqua Terrarium",
    "artis": "Yanagi Nagi"
   },
   {
    "lagu": "https://l.top4top.io/m_2353739d91.mp3",
    "judul": "Mogu Mogu Yummy!",
    "artis": "Nekomata Okayu"
   },
   {
    "lagu": "https://k.top4top.io/m_2353vktfc1.mp3",
    "judul": "KING",
    "artis": "Kanaria"
   },
   {
    "lagu": "https://j.top4top.io/m_2353i5okx1.mp3",
    "judul": "Blue Bird",
    "artis": "Ikimonogakari"
   },
   {
    "lagu": "https://f.top4top.io/m_23537o6xd1.mp3",
    "judul": "Hanabi",
    "artis": "Ikimonogakari"
   },
   {
    "lagu": "https://i.top4top.io/m_2353bee3l1.mp3",
    "judul": "asphyxia",
    "artis": "Cö Shu Nie"
   },
   {
    "lagu": "https://g.top4top.io/m_2353lzp0v1.mp3",
    "judul": "Kago no Naka ni Tori",
    "artis": "yourness"
   },
   {
    "lagu": "https://h.top4top.io/m_2353st9t61.mp3",
    "judul": "Papapa",
    "artis": "Shuka Saitō"
   },
   {
    "lagu": "https://k.top4top.io/m_2353zz3ez1.mp3",
    "judul": "homura",
    "artis": "LiSA"
   },
   {
    "lagu": "https://j.top4top.io/m_23539xjw71.mp3",
    "judul": "JUSTadICE",
    "artis": "Seiko Oomori"
   },
   {
    "lagu": "https://h.top4top.io/m_23537xro21.mp3",
    "judul": "Here",
    "artis": "JUNNA"
   },
   {
    "lagu": "https://e.top4top.io/m_2353ekegb1.mp3",
    "judul": "Wa -cycle-",
    "artis": "Hana Itoki"
   },
   {
    "lagu": "https://e.top4top.io/m_2352hlews1.mp3",
    "judul": "Hitorigoto",
    "artis": "ClariS"
   }
]
